pyapibp/__init__.py
pyapibp/_blueprints.py
pyapibp/_questions.py
pyapibp/_style.py
pyapibp/_validators.py
pyapibp/entry.py
pyapibp/pyapibp.py
tests/__init__.py
tests/__main__.py
pyapibp-0.1.1.dist-info/AUTHORS.rst
pyapibp-0.1.1.dist-info/LICENSE
pyapibp-0.1.1.dist-info/METADATA
pyapibp-0.1.1.dist-info/WHEEL
pyapibp-0.1.1.dist-info/entry_points.txt
pyapibp-0.1.1.dist-info/top_level.txt
pyapibp-0.1.1.dist-info/RECORD
