Metadata-Version: 2.1
Name: pyapibp
Version: 0.1.1
Summary: Python boilerplate code generator to easily start building API's
Home-page: https://github.com/markmelnic/pyapibp
Author: Mark Melnic
Author-email: me@markmelnic.com
License: MIT
Keywords: python flask fastapi django api boilerplate code blueprint generator
Platform: UNKNOWN
Classifier: Natural Language :: English
Classifier: Development Status :: 3 - Alpha
Classifier: Intended Audience :: Developers
Classifier: License :: OSI Approved :: MIT License
Classifier: Programming Language :: Python :: 3
Classifier: Programming Language :: Python :: 3.6
Classifier: Programming Language :: Python :: 3.7
Classifier: Programming Language :: Python :: 3.8
Classifier: Programming Language :: Python :: 3.9
Requires-Dist: pathvalidate
Requires-Dist: PyInquirer
